dwipy/IO/__init__.py
dwipy/IO/converters.py
dwipy/IO/gradient_table.py
dwipy/IO/misc.py
dwipy/__init__.py
dwipy/constants.py
dwipy/metrics/__init__.py
dwipy/metrics/adc.py
dwipy/mrtrix/__init__.py
dwipy/mrtrix/gradient_table.py
dwipy/mrtrixpy.py
dwipy/pipeline.py
dwipy/qa.py
dwipy/rescuer.py
dwipy-0.3.0.dist-info/LICENSE
dwipy-0.3.0.dist-info/WHEEL
dwipy-0.3.0.dist-info/METADATA
dwipy-0.3.0.dist-info/RECORD
