Metadata-Version: 2.1
Name: dwipy
Version: 0.3.0
Summary: DWI anaylysis pipeline
Home-page: https://github.com/svdvoort/dwipy
License: MIT
Requires-Python: >=3.7.0,<3.9
Classifier: Development Status :: 3 - Alpha
Classifier: Intended Audience :: Developers
Classifier: License :: OSI Approved :: MIT License
Classifier: Operating System :: OS Independent
Classifier: Programming Language :: Python :: 3
Classifier: Programming Language :: Python :: 3.7
Classifier: Programming Language :: Python :: 3.8
Classifier: Topic :: Software Development :: Libraries :: Python Modules
Requires-Dist: SimpleITK (>=2.0.2,<3.0.0)
Requires-Dist: numpy (>=1.19.4,<2.0.0)
Requires-Dist: opencv-python (>=4.4.0,<5.0.0)
Requires-Dist: pydicom (>=2.1.1,<3.0.0)
Requires-Dist: pytesseract (>=0.3.6,<0.4.0)
Project-URL: Repository, https://github.com/svdvoort/dwipy
